dcplib/__init__.py
dcplib/aws_secret.py
dcplib/config.py
dcplib/errors.py
dcplib/networking.py
dcplib/s3_multipart.py
dcplib/aws/__init__.py
dcplib/aws/_boto3_loader.py
dcplib/aws/clients.py
dcplib/aws/resources.py
dcplib/aws/sqs_handler.py
dcplib/aws/sqs/__init__.py
dcplib/checksumming_io/__init__.py
dcplib/checksumming_io/_crc32c.py
dcplib/checksumming_io/checksumming_buffered_reader.py
dcplib/checksumming_io/checksumming_sink.py
dcplib/checksumming_io/s3_etag.py
dcplib/component_agents/__init__.py
dcplib/component_agents/hal_agent.py
dcplib/component_agents/ingest_api_agent.py
dcplib/component_entities/__init__.py
dcplib/component_entities/ingest_entities.py
dcplib/etl/__init__.py
dcplib/media_types/__init__.py
dcplib/media_types/dcp_media_type.py
dcplib/media_types/media_type.py
dcplib/security/__init__.py
dcplib/security/authn.py
dcplib/security/authz.py
dcplib/security/dcp_service_account.py
dcplib/test_helpers/__init__.py
dcplib-3.12.0.dist-info/METADATA
dcplib-3.12.0.dist-info/RECORD
dcplib-3.12.0.dist-info/WHEEL
dcplib-3.12.0.dist-info/top_level.txt
tests/aws/__init__.py
tests/aws/test_sqs_handler.py
tests/checksumming_io/__init__.py
tests/checksumming_io/test_checksumming_buffered_reader.py
tests/checksumming_io/test_checksumming_sink.py
tests/component_agents/__init__.py
tests/component_agents/test_hal_agent.py
tests/media_types/__init__.py
tests/media_types/test_dcp_media_type.py
tests/media_types/test_media_type.py
tests/security/__init__.py
tests/security/test_authn.py
tests/security/test_authz.py
tests/security/test_dcp_service_account.py
